[
    {
        "name": "Abdallah Magdi Matar",
        "email": "abdallahmatar10@gmail.com",
        "address": "koubri kamal",
        "phone": "01204267500",
        "password": "$2y$10$nU6Xu5c364mNM51fWyTqYOHQkj1tfVJ36MmllnWvoP5pTsj\/6\/KjO"
    },
    {
        "name": "Abdalla magdy beder\u202c\u200f",
        "email": "abdallahmatar100@gmail.com",
        "address": "koubri kamal23",
        "phone": "01505230513",
        "password": "$2y$10$cWiH0GUOUjHUgCoJH3uCcuwvQXaMPl9oD5MJQicenr3MNEjh1az5."
    },
    {
        "name": "Abdalla magdy beder\u202c\u200f",
        "email": "abdallahmatar1000@gmail.com",
        "address": "koubri kamal",
        "phone": "01204267500",
        "password": "$2y$10$NHLypMHXcD\/qGqL\/vlRub.p3.0ZAR3jMYjBlRi54M00xknPA6VABW"
    },
    {
        "name": "Ali",
        "email": "ali10@gmail.com",
        "address": "koubri kamal",
        "phone": "01009128305",
        "password": "$2y$10$QGGf90FjYhiM3LBKQehaZO1FhfRAWke7W2vXsL6zCDmGb2C2Hd75a"
    }
]